Metadata-Version: 1.1
Name: pydataset
Version: 0.1.1
Summary: Provides instant access to many popular datasets right from Python (in dataframe structure).
Home-page: https://github.com/iamaziz/PyDataset
Author: Aziz Alto
Author-email: iamaziz.alto@gmail.com
License: MIT
Download-URL: https://github.com/iamaziz/PyDataset/tarball/0.1.1
Platform: UNKNOWN
